Workbook

Sheet Summary Budget
A1: TURNER THEOLOGICAL SEMINARY
A2: Lilly Endowment — Exploring Christian Practices Initiative
A3: SUMMARY BUDGET | Pathway-Aligned Strategic Taper | Grant Request: $2,200,000 | Five-Year Period 2026–2030
A5: Budget Category / Line Item | B5: 2026 | C5: 2027 | D5: 2028 | E5: 2029 | F5: 2030 | G5: TOTAL
A6: INCOME
A7: Lilly Endowment Grant | B7: 500000 | C7: 470000 | D7: 440000 | E7: 405000 | F7: 385000 | G7: =SUM(B7:F7) -> 2200000
A8: TOTAL INCOME | B8: =B7 -> 500000 | C8: =C7 -> 470000 | D8: =D7 -> 440000 | E8: =E7 -> 405000 | F8: =F7 -> 385000 | G8: =SUM(B8:F8) -> 2200000
A10: EXPENSES
A11: Program Leadership | B11: 145000 | C11: 140000 | D11: 125000 | E11: 105000 | F11: 90000 | G11: =SUM(B11:F11) -> 605000
A12: Fringe Benefits (20% of Personnel) | B12: =B11*20% -> 29000 | C12: =C11*20% -> 28000 | D12: =D11*20% -> 25000 | E12: =E11*20% -> 21000 | F12: =F11*20% -> 18000 | G12: =SUM(B12:F12) -> 121000
A13: Calling Pathway Support (JLWLA) | B13: 40000 | C13: 38000 | D13: 36000 | E13: 32000 | F13: 30000 | G13: =SUM(B13:F13) -> 176000
A14: Care Pathway Support (Sankofa CPE LLC) | B14: 40000 | C14: 38000 | D14: 36000 | E14: 32000 | F14: 30000 | G14: =SUM(B14:F14) -> 176000
A15: Community Pathway Support (Salvation & Social Justice) | B15: 42000 | C15: 40000 | D15: 38000 | E15: 35000 | F15: 32000 | G15: =SUM(B15:F15) -> 187000
A16: Renewal Pathway Support (TLCH) | B16: 40000 | C16: 38000 | D16: 36000 | E16: 32000 | F16: 30000 | G16: =SUM(B16:F16) -> 176000
A17: Sixth Episcopal District Congregational Engagement Support | B17: 10000 | C17: 10000 | D17: 10000 | E17: 10000 | F17: 10000 | G17: =SUM(B17:F17) -> 50000
A18: Retreats, Cohorts & Community Engagement | B18: 45000 | C18: 38000 | D18: 34000 | E18: 30000 | F18: 25000 | G18: =SUM(B18:F18) -> 172000
A19: Shared Formation & Participant Engagement Activities | B19: 20000 | C19: 15000 | D19: 12000 | E19: 10000 | F19: 8000 | G19: =SUM(B19:F19) -> 65000
A20: Communications & Dissemination | B20: 14000 | C20: 13000 | D20: 11000 | E20: 10000 | F20: 8000 | G20: =SUM(B20:F20) -> 56000
A21: Evaluation & Assessment | B21: 41000 | C21: 38000 | D21: 40000 | E21: 45000 | F21: 50000 | G21: =SUM(B21:F21) -> 214000
A22: Sustainability & Replication | B22: 8190 | C22: 10000 | D22: 14000 | E22: 22000 | F22: 39000 | G22: =SUM(B22:F22) -> 93190
A23: Technology & Hybrid Infrastructure | B23: 12000 | C23: 10619 | D23: 11048 | E23: 11714 | F23: 6286 | G23: =SUM(B23:F23) -> 51667
A24: DIRECT COSTS SUBTOTAL | B24: =SUM(B11:B23) -> 486190 | C24: =SUM(C11:C23) -> 456619 | D24: =SUM(D11:D23) -> 428048 | E24: =SUM(E11:E23) -> 395714 | F24: =SUM(F11:F23) -> 376286 | G24: =SUM(B24:F24) -> 2142857
A25: Indirect Costs (difference to grant request; approximately 5% of direct costs) | B25: =B24*0.05 -> 24309.5 | C25: =C24*0.05 -> 22830.95 | D25: =D24*0.05 -> 21402.4 | E25: =E24*0.05 -> 19785.7 | F25: =F24*0.05 -> 18814.3 | G25: =SUM(B25:F25) -> 107142.85
A26: TOTAL EXPENSES | B26: =B24+B25 -> 510499.5 | C26: =C24+C25 -> 479449.95 | D26: =D24+D25 -> 449450.4 | E26: =E24+E25 -> 415499.7 | F26: =F24+F25 -> 395100.3 | G26: =SUM(B26:F26) -> 2249999.9
A28: IN-KIND COST-SHARE (Institutional Leadership, Facilities, Administrative Infrastructure — NOT charged to grant) | B28: 108900 | C28: 108900 | D28: 108900 | E28: 108900 | F28: 108900 | G28: =SUM(B28:F28) -> 544500
A30: Strategic Budget Notes
A31: The budget intentionally tapers during Years 4–5 to demonstrate long-term institutional sustainability and reduced dependency on grant funding.
A32: Budget categories directly reinforce the four pathways of formation: Calling, Care, Community, and Renewal.
A33: The final two years emphasize institutional integration, sustainability, evaluation, and replication rather than permanent grant dependence.

Sheet Line-Item Budget
A1: TURNER THEOLOGICAL SEMINARY — LINE-ITEM BUDGET
A2: Lilly Endowment — Exploring Christian Practices Initiative | Formula-Driven Budget Detail
A4: Category / Line Item | B4: Budget Basis / Notes | C4: 2026 | D4: 2027 | E4: 2028 | F4: 2029 | G4: 2030 | H4: TOTAL
A5: Personnel & Leadership Support | B5: Grant-funded portion of project personnel and leadership support; tapers in later years as institutional integration increases. | C5: 145000 | D5: 140000 | E5: 125000 | F5: 105000 | G5: 90000 | H5: =SUM(C5:G5) -> 605000
A6: Fringe Benefits (20% of Personnel) | B6: Calculated at 20% of Personnel & Leadership Support. | C6: =C5*20% -> 29000 | D6: =D5*20% -> 28000 | E6: =E5*20% -> 25000 | F6: =F5*20% -> 21000 | G6: =G5*20% -> 18000 | H6: =SUM(C6:G6) -> 121000
A7: Calling Pathway Support (JLWLA) | B7: Calling pathway: women in ministry cohorts, mentoring, discernment retreats, prayer and scripture-reflection activities. | C7: 40000 | D7: 38000 | E7: 36000 | F7: 32000 | G7: 30000 | H7: =SUM(C7:G7) -> 176000
A8: Care Pathway Support (Sankofa CPE LLC) | B8: Care pathway: pastoral listening, trauma-informed spiritual care, grief accompaniment, and reflective ministry formation. | C8: 40000 | D8: 38000 | E8: 36000 | F8: 32000 | G8: 30000 | H8: =SUM(C8:G8) -> 176000
A9: Community Pathway Support (Salvation & Social Justice) | B9: Community pathway: reconciliation circles, civic compassion, justice-centered engagement, and faith-rooted public witness. | C9: 42000 | D9: 40000 | E9: 38000 | F9: 35000 | G9: 32000 | H9: =SUM(C9:G9) -> 187000
A10: Renewal Pathway Support (TLCH) | B10: Renewal pathway: coaching cohorts, sabbath practices, wellness retreats, accountability circles, and leadership renewal. | C10: 40000 | D10: 38000 | E10: 36000 | F10: 32000 | G10: 30000 | H10: =SUM(C10:G10) -> 176000
A11: Sixth Episcopal District Congregational Engagement Support | C11: 10000 | D11: 10000 | E11: 10000 | F11: 10000 | G11: 10000 | H11: =SUM(C11:G11) -> 50000
A12: Retreats, Cohorts & Community Engagement | B12: Residential and community-based formation experiences, cohort convenings, participant gatherings, and contextual engagement. | C12: 45000 | D12: 38000 | E12: 34000 | F12: 30000 | G12: 25000 | H12: =SUM(C12:G12) -> 172000
A13: Shared Formation & Participant Engagement Activities | B13: Cross-pathway participant materials, facilitator resources, shared spiritual practice resources, and formation supports. | C13: 20000 | D13: 15000 | E13: 12000 | F13: 10000 | G13: 8000 | H13: =SUM(C13:G13) -> 65000
A14: Communications & Dissemination | B14: Digital engagement, storytelling, webinars, participant testimonials, program updates, and dissemination materials. | C14: 14000 | D14: 13000 | E14: 11000 | F14: 10000 | G14: 8000 | H14: =SUM(C14:G14) -> 56000
A15: Evaluation & Assessment | B15: Formative and summative assessment, surveys, focus groups, data analysis, reporting, and continuous improvement. | C15: 41000 | D15: 38000 | E15: 40000 | F15: 45000 | G15: 50000 | H15: =SUM(C15:G15) -> 214000
A16: Sustainability & Replication | B16: Replication toolkit, fundraising readiness, advancement integration, sustainability planning, and post-grant transition. | C16: 8190 | D16: 10000 | E16: 14000 | F16: 22000 | G16: 39000 | H16: =SUM(C16:G16) -> 93190
A17: Technology & Hybrid Infrastructure | B17: Hybrid learning systems, digital participant engagement tools, data/reporting supports, and online access infrastructure. | C17: 12000 | D17: 10619 | E17: 11048 | F17: 11714 | G17: 6286 | H17: =SUM(C17:G17) -> 51667
A18: DIRECT COSTS SUBTOTAL | B18: Formula sum of all direct cost line items. | C18: =SUM(C5:C17) -> 486190 | D18: =SUM(D5:D17) -> 456619 | E18: =SUM(E5:E17) -> 428048 | F18: =SUM(F5:F17) -> 395714 | G18: =SUM(G5:G17) -> 376286 | H18: =SUM(C18:G18) -> 2142857
A19: Indirect Costs | B19: Calculated as the amount required to reconcile total expenses to the grant request by year; approximately 5% of direct costs. | C19: =C18*0.05 -> 24309.5 | D19: =D18*0.05 -> 22830.95 | E19: =E18*0.05 -> 21402.4 | F19: =F18*0.05 -> 19785.7 | G19: =G18*0.05 -> 18814.3 | H19: =SUM(C19:G19) -> 107142.85
A20: TOTAL GRANT EXPENSES | B20: Direct costs plus indirect costs. | C20: =C18+C19 -> 510499.5 | D20: =D18+D19 -> 479449.95 | E20: =E18+E19 -> 449450.4 | F20: =F18+F19 -> 415499.7 | G20: =G18+G19 -> 395100.3 | H20: =SUM(C20:G20) -> 2249999.9

Sheet Budget Narrative
A1: TURNER THEOLOGICAL SEMINARY — BUDGET NARRATIVE
A2: Lilly Endowment — Exploring Christian Practices Initiative | Grant Request: $2,200,000
A4: Budget Category | B4: Narrative Justification | C4: Alignment to Proposal | D4: Sustainability / Taper Rationale
A5: Personnel & Leadership Support | B5: Supports grant-funded portions of leadership, coordination, program management, engagement, and implementation needed to carry out the four-pathway model. | C5: Provides operational capacity for Calling, Care, Community, and Renewal pathway implementation. | D5: Personnel costs taper in later years as institutional support, partner systems, and ongoing operations absorb more functions.
A6: Fringe Benefits | B6: Calculated at 20% of personnel support to reflect benefits-related costs associated with grant-supported staff time. | C6: Ensures personnel support is budgeted realistically and responsibly. | D6: Fringe tapers automatically with personnel through formula-driven calculations.
A7: Calling Pathway Support (JLWLA) | B7: Supports women in ministry cohorts, mentoring, vocational discernment, retreats, prayer practices, scripture reflection, and leadership formation activities. | C7: Directly funds the Calling pathway and reinforces the proposal’s focus on vocation, discernment, and women’s leadership formation. | D7: Costs taper as cohort models are established and integrated into Turner’s ongoing formation infrastructure.
A8: Care Pathway Support (Sankofa CPE LLC) | B8: Supports trauma-informed spiritual care, pastoral listening, grief accompaniment, theological reflection, community-based care training, and wellness workshops. | C8: Directly funds the Care pathway and strengthens the partnership with Sankofa CPE LLC. | D8: Costs taper as training models and partner protocols are established for ongoing use.
A9: Community Pathway Support (Salvation & Social Justice) | B9: Supports reconciliation circles, civic compassion work, justice-centered engagement, testimony and story-sharing, and faith-rooted public witness. | C9: Directly funds the Community pathway and strengthens the partnership with Salvation and Social Justice. | D9: Costs taper as community engagement models and shared partner infrastructure mature.
A10: Renewal Pathway Support (TLCH) | B10: Supports coaching cohorts, sabbath practices, wellness retreats, guided reflection, accountability circles, prayer partnerships, and leadership renewal activities. | C10: Directly funds the Renewal pathway and balances investment with the Calling pathway to underscore renewal as a core element of the Turner Model. | D10: Costs taper as TLCH becomes embedded in Turner’s ongoing leadership development and coaching framework.
A11: Retreats, Cohorts & Community Engagement | B11: Supports residential formation experiences, cohort gatherings, community-based engagement, retreats, participant convenings, and formation settings inside and outside congregational contexts. | C11: Responds to Lilly’s emphasis on multiplying opportunities and expanding access to settings where individuals can explore Christian practices. | D11: Costs taper as Turner institutionalizes the cohort and retreat model and leverages partner sites.
A12: Shared Formation & Participant Engagement Activities | B12: Supports cross-pathway materials, facilitator resources, shared participant supports, formation guides, and engagement tools used across the initiative. | C12: Provides flexible support for integrated participant experience without duplicating pathway-specific allocations. | D12: Reduced relative to pathway categories to keep the budget aligned with direct pathway implementation.
A13: Communications & Dissemination | B13: Supports storytelling, digital engagement, webinars, leadership gatherings, program updates, participant testimonials, and dissemination of lessons learned. | C13: Aligns with the proposal’s communication strategy for sharing insights with churches, ministry leaders, theological educators, and faith-based organizations. | D13: Costs taper as communication tools and templates are developed and integrated into institutional channels.
A14: Evaluation & Assessment | B14: Supports formative and summative evaluation, participant surveys, focus groups, stakeholder feedback, retention tracking, attendance data, survey analysis, program completion measures, and reporting. | C14: Aligns with the proposal’s evaluation plan and supports data-driven decision-making, continuous improvement, and replication. | D14: Evaluation investment shifts toward summative assessment and final reporting during the last two years.
A15: Sustainability & Replication | B15: Supports replication toolkit development, sustainability planning, advancement integration, fundraising readiness, partner transition planning, and post-grant continuation efforts. | C15: Aligns with the proposal’s commitment to institutional integration and long-term replication beyond the grant period. | D15: This line increases over time to demonstrate intentional transition from launch funding to sustainability infrastructure.
... A17: Indirect Costs | B17: Supports allowable administrative and institutional costs associated with managing the grant. | C17: Ensures responsible grant administration without overbuilding overhead. | D17: Kept modest and formula-driven to emphasize stewardship and maximize programmatic investment.

Sheet Assumptions
A1: BUDGET ASSUMPTIONS
A3: Assumption | B3: Value / Basis | C3: 2026 | D3: 2027 | E3: 2028 | F3: 2029 | G3: 2030 | H3: TOTAL
A4: Grant Request | B4: $2,200,000 over five years
A5: Grant Period | B5: 2026–2030
A6: Budget Strategy | B6: Strategic taper: higher launch investment, lower end-of-grant dependency
A7: Fringe Rate | B7: 20% of Personnel & Leadership Support
A8: Indirect Cost Method | B8: Reconciles annual total expenses to annual grant request; approximately 5% of direct costs
A9: Pathway Structure | B9: Calling, Care, Community, Renewal
A10: Sustainability Strategy | B10: Institutional integration, advancement, partner infrastructure, replication toolkit
A11: In-kind Support | B11: Institutional leadership, facilities, operations, administrative infrastructure
A13: Annual Grant Request | C13: 2026 | D13: 2027 | E13: 2028 | F13: 2029 | G13: 2030 | H13: TOTAL
A14: Lilly Endowment Grant | C14: 500000 | D14: 470000 | E14: 440000 | F14: 405000 | G14: 385000 | H14: =SUM(C14:G14) -> 2200000
A16: Direct Cost Target | C16: 2026 | D16: 2027 | E16: 2028 | F16: 2029 | G16: 2030 | H16: TOTAL
A17: Direct Costs | C17: 476190 | D17: 447619 | E17: 419048 | F17: 385714 | G17: 366667 | H17: =SUM(C17:G17) -> 2095238
A19: Indirect Cost Target | C19: 2026 | D19: 2027 | E19: 2028 | F19: 2029 | G19: 2030 | H19: TOTAL
A20: Indirect Costs | C20: =C14-C17 -> 23810 | D20: =D14-D17 -> 22381 | E20: =E14-E17 -> 20952 | F20: =F14-F17 -> 19286 | G20: =G14-G17 -> 18333 | H20: =SUM(C20:G20) -> 104762

Sheet Formula Checks
A1: FORMULA CHECKS
A3: Check | B3: 2026 | C3: 2027 | D3: 2028 | E3: 2029 | F3: 2030 | G3: TOTAL
A4: Income equals total expenses | B4: ='Summary Budget'!B8-'Summary Budget'!B26 -> -10499.5 | C4: ='Summary Budget'!C8-'Summary Budget'!C26 -> -9449.95 | D4: ='Summary Budget'!D8-'Summary Budget'!D26 -> -9450.4 | E4: ='Summary Budget'!E8-'Summary Budget'!E26 -> -10499.7 | F4: ='Summary Budget'!F8-'Summary Budget'!F26 -> -10100.3 | G4: ='Summary Budget'!G8-'Summary Budget'!G26 -> -49999.85
A5: Summary direct costs = line-item direct costs | B5: ='Summary Budget'!B24-'Line-Item Budget'!C18 -> 0 | C5: ='Summary Budget'!C24-'Line-Item Budget'!D18 -> 0 | D5: ='Summary Budget'!D24-'Line-Item Budget'!E18 -> 0 | E5: ='Summary Budget'!E24-'Line-Item Budget'!F18 -> 0 | F5: ='Summary Budget'!F24-'Line-Item Budget'!G18 -> 0 | G5: ='Summary Budget'!G24-'Line-Item Budget'!H18 -> 0
A6: Summary total = $2.2M | G6: ='Summary Budget'!G8-2200000 -> 0
A7: Fringe equals 20% of personnel | B7: ='Summary Budget'!B12-'Summary Budget'!B11*20% -> 0 | C7: ='Summary Budget'!C12-'Summary Budget'!C11*20% -> 0 | D7: ='Summary Budget'!D12-'Summary Budget'!D11*20% -> 0 | E7: ='Summary Budget'!E12-'Summary Budget'!E11*20% -> 0 | F7: ='Summary Budget'!F12-'Summary Budget'!F11*20% -> 0 | G7: ='Summary Budget'!G12-'Summary Budget'!G11*20% -> 0
